ztime/__init__.py
ztime-0.1.0.dist-info/METADATA
ztime-0.1.0.dist-info/WHEEL
ztime-0.1.0.dist-info/licenses/LICENSE
ztime-0.1.0.dist-info/RECORD
